ddnspod/__init__.py
ddnspod/ddns.py
ddnspod-0.2.0.dist-info/DESCRIPTION.rst
ddnspod-0.2.0.dist-info/METADATA
ddnspod-0.2.0.dist-info/RECORD
ddnspod-0.2.0.dist-info/WHEEL
ddnspod-0.2.0.dist-info/metadata.json
ddnspod-0.2.0.dist-info/top_level.txt
