Metadata-Version: 2.0
Name: ddnspod
Version: 0.2.0
Summary: ddnspod
Home-page: https://github.com/maguowei/ddnspod
Author: maguowei
Author-email: imaguowei@gmail.com
License: The MIT License (MIT)
Platform: UNKNOWN
Classifier: Programming Language :: Python
Classifier: Programming Language :: Python :: 3
Classifier: Programming Language :: Python :: 3.3
Classifier: Programming Language :: Python :: 3.4
Classifier: Programming Language :: Python :: 3.5
Requires-Dist: requests (>=2.9.1)
